scrappit/__init__.py
scrappit/api.py
scrappit/common.py
scrappit/dispatcher.py
scrappit/scheduler.py
scrappit-0.3.0.dist-info/METADATA
scrappit-0.3.0.dist-info/WHEEL
scrappit-0.3.0.dist-info/licenses/LICENSE
scrappit-0.3.0.dist-info/RECORD
